LICENSE
MANIFEST.in
README.md
requirements.txt
setup.py
PyCMeKG.egg-info/PKG-INFO
PyCMeKG.egg-info/SOURCES.txt
PyCMeKG.egg-info/dependency_links.txt
PyCMeKG.egg-info/top_level.txt
pyCMeKG/__init__.py
pyCMeKG/knowledgeGraph.py
pyCMeKG.egg-info/PKG-INFO
pyCMeKG.egg-info/SOURCES.txt
pyCMeKG.egg-info/dependency_links.txt
pyCMeKG.egg-info/top_level.txt
pyCMeKG/model/cmekg.pkl