Metadata-Version: 1.1
Name: PyCMeKG
Version: 0.2.5
Summary: Chinese Medical Knowledge Graph
Home-page: https://github.com/king-yyf/PyCMeKG
Author: Yunfei Yang
Author-email: yfy@pku.edu.cn
License: MIT
Platform: UNKNOWN
Classifier: License :: OSI Approved :: MIT License
Classifier: Intended Audience :: Developers
Classifier: Operating System :: OS Independent
Classifier: Programming Language :: Python :: 3
